{"4303": [{"prices": {"SDR": ["00000390", ""], "SDS": ["00000380", ""]}, "toc": "RWB", "route": "00000"}], "4455": [{"prices": {"SDR": ["00000930", ""], "SDS": ["00000910", ""]}, "toc": "RWB", "route": "00000"}], "4304": [{"prices": {"SDR": ["00000330", ""], "SDS": ["00000310", ""]}, "toc": "RWB", "route": "00000"}], "4327": [{"prices": {"SDR": ["00000840", ""], "SDS": ["00000830", ""]}, "toc": "RWB", "route": "00000"}], "4435": [{"prices": {"SDR": ["00000330", ""], "SDS": ["00000320", ""]}, "toc": "RWB", "route": "00000"}], "4434": [{"prices": {"SVR": ["00002030", "8A"], "SDR": ["00001270", ""], "SDS": ["00001250", ""]}, "toc": "RWB", "route": "00000"}], "4433": [{"prices": {"SDR": ["00000450", ""], "SDS": ["00000430", ""]}, "toc": "RWB", "route": "00000"}], "4432": [{"prices": {"SDR": ["00000510", ""], "SDS": ["00000480", ""]}, "toc": "RWB", "route": "00000"}], "4470": [{"prices": {"SDR": ["00000810", ""], "SDS": ["00000800", ""]}, "toc": "RWB", "route": "00000"}], "4473": [{"prices": {"SVR": ["00002200", "8A"], "SDR": ["00001260", ""], "SDS": ["00001250", ""]}, "toc": "RWB", "route": "00000"}], "4458": [{"prices": {"SVR": ["00002060", "8A"], "SDR": ["00001120", ""], "SDS": ["00001100", ""]}, "toc": "RWB", "route": "00000"}], "4416": [{"prices": {"SDR": ["00000780", ""], "SDS": ["00000740", ""]}, "toc": "RWB", "route": "00000"}], "4412": [{"prices": {"SDR": ["00000950", ""], "SDS": ["00000930", ""]}, "toc": "RWB", "route": "00000"}], "4312": [{"prices": {"SVR": ["00002330", "8A"], "SDR": ["00001390", ""], "SDS": ["00001380", ""]}, "toc": "RWB", "route": "00000"}], "4313": [{"prices": {"SVR": ["00002200", "8A"], "SDR": ["00001310", ""], "SDS": ["00001290", ""]}, "toc": "RWB", "route": "00000"}], "4314": [{"prices": {"SVR": ["00002330", "8A"], "SDR": ["00001610", ""], "SDS": ["00001600", ""]}, "toc": "RWB", "route": "00000"}], "4334": [{"prices": {"SVR": ["00002200", "8A"], "SDR": ["00001260", ""], "SDS": ["00001250", ""]}, "toc": "RWB", "route": "00000"}], "4335": [{"prices": {"SDR": ["00000270", ""], "SDS": ["00000260", ""]}, "toc": "RWB", "route": "00000"}], "4440": [{"prices": {"SVR": ["00002330", "8A"], "SDR": ["00001610", ""], "SDS": ["00001600", ""]}, "toc": "RWB", "route": "00000"}], "4445": [{"prices": {"SDR": ["00000820", ""], "SDS": ["00000810", ""]}, "toc": "RWB", "route": "00000"}], "4469": [{"prices": {"SVR": ["00002200", "8A"], "SDR": ["00001310", ""], "SDS": ["00001290", ""]}, "toc": "RWB", "route": "00000"}], "4355": [{"prices": {"SDR": ["00000920", ""], "SDS": ["00000900", ""]}, "toc": "RWB", "route": "00000"}], "4356": [{"prices": {"SVR": ["00002060", "8A"], "SDR": ["00001040", ""], "SDS": ["00001010", ""]}, "toc": "RWB", "route": "00000"}], "4357": [{"prices": {"SVR": ["00002200", "8A"], "SDR": ["00001250", ""], "SDS": ["00001240", ""]}, "toc": "RWB", "route": "00000"}], "H075": [{"prices": {"SVR": ["00004070", "8A"], "SDR": ["00003480", ""], "SDS": ["00002560", ""]}, "toc": "RWB", "route": "00962"}], "4463": [{"prices": {"SVR": ["00002060", "8A"], "SDR": ["00001110", ""], "SDS": ["00001090", ""]}, "toc": "RWB", "route": "00000"}], "4460": [{"prices": {"SVR": ["00002060", "8A"], "SDR": ["00001110", ""], "SDS": ["00001090", ""]}, "toc": "RWB", "route": "00000"}], "4479": [{"prices": {"SVR": ["00002200", "8A"], "SDR": ["00001250", ""], "SDS": ["00001240", ""]}, "toc": "RWB", "route": "00000"}], "4409": [{"prices": {"SVR": ["00002350", "8A"], "SDR": ["00001540", ""], "SDS": ["00001520", ""]}, "toc": "RWB", "route": "00000"}], "4422": [{"prices": {"SDR": ["00000230", ""], "SDS": ["00000220", ""]}, "toc": "RWB", "route": "00000"}], "4421": [{"prices": {"SDR": ["00000670", ""], "SDS": ["00000660", ""]}, "toc": "RWB", "route": "00000"}], "4426": [{"prices": {"SVR": ["00001930", "8A"], "SDR": ["00001220", ""], "SDS": ["00001120", ""]}, "toc": "RWB", "route": "00000"}]}