{"5462": [{"prices": {"SDR": ["00002140", ""], "CDR": ["00001260", "B3"], "SDS": ["00001130", ""]}, "toc": "NSC", "route": "00000", "direction": "S"}], "5426": [{"prices": {"SVR": ["00003050", "4B"], "SDR": ["00003950", ""], "CDR": ["00002250", "C0"], "SDS": ["00001970", ""]}, "toc": "NSC", "route": "00000", "direction": "S"}], "0035": [], "5333": [{"prices": {"SDR": ["00001590", ""], "CDR": ["00000980", "B3"], "SDS": ["00000870", ""]}, "toc": "NSC", "route": "00000", "direction": "S"}], "7222": [{"prices": {"SVR": ["00003920", "4B"], "SDR": ["00005230", ""], "CDR": ["00003110", "C0"], "SDS": ["00002680", ""]}, "toc": "NSE", "route": "00200", "direction": "S"}, {"prices": {"SDS": ["00002510", ""], "SVR": ["00003690", "4J"], "SDR": ["00004520", ""], "CDR": ["00002090", "TN"], "CDS": ["00002080", "TN"]}, "toc": "NSE", "route": "00703", "direction": "S"}], "5470": [{"prices": {}, "toc": "FCC", "route": "00028", "direction": "S"}], "5211": [{"prices": {"SDS": ["00001340", ""], "SVR": ["00002100", "4B"], "SDR": ["00002140", ""], "CDR": ["00001300", "B3"], "CDS": ["00001290", "B3"]}, "toc": "NSC", "route": "00000", "direction": "S"}], "5495": [{"prices": {"SDR": ["00001520", ""], "CDR": ["00000830", "B3"], "SDS": ["00000760", ""]}, "toc": "NSC", "route": "00000", "direction": "S"}], "0839": [{"prices": {"SDR": ["00003630", ""], "SDS": ["00002140", ""]}, "toc": "NSC", "route": "00754", "direction": "S"}], "5491": [{"prices": {"SDR": ["00001340", ""], "CDR": ["00000730", "B3"], "SDS": ["00000700", ""]}, "toc": "NSC", "route": "00000", "direction": "S"}], "5492": [{"prices": {"SDS": ["00000530", ""], "SDR": ["00001050", ""], "CDR": ["00000530", "B3"], "CDS": ["00000520", "B3"]}, "toc": "NSC", "route": "00000", "direction": "S"}], "5493": [{"prices": {"SDR": ["00001850", ""], "CDR": ["00001030", "B3"], "SDS": ["00000940", ""]}, "toc": "NSC", "route": "00000", "direction": "R"}], "5252": [{"prices": {"SDR": ["00001810", ""], "CDR": ["00001300", "B3"], "SDS": ["00001290", ""]}, "toc": "NSC", "route": "00000", "direction": "S"}], "5253": [{"prices": {"SDS": ["00001340", ""], "SVR": ["00002100", "4B"], "SDR": ["00001810", ""], "CDR": ["00001300", "B3"], "CDS": ["00001290", "B3"]}, "toc": "NSC", "route": "00000", "direction": "S"}], "5416": [{"prices": {"SDR": ["00001340", ""], "CDR": ["00000830", "B3"], "SDS": ["00000710", ""]}, "toc": "NSC", "route": "00000", "direction": "S"}], "5450": [{"prices": {"SDR": ["00002140", ""], "CDR": ["00001200", "B3"], "SDS": ["00001140", ""]}, "toc": "NSC", "route": "00000", "direction": "S"}], "5490": [{"prices": {"SDR": ["00000700", ""], "CDR": ["00000390", "B3"], "SDS": ["00000370", ""]}, "toc": "NSC", "route": "00000", "direction": "R"}], "5258": [{"prices": {"SDR": ["00001840", ""], "CDR": ["00001290", "B3"], "SDS": ["00001210", ""]}, "toc": "NSC", "route": "00000", "direction": "S"}], "1072": [{"prices": {"SVR": ["00003170", "4B"], "SDR": ["00004170", ""], "CDR": ["00002360", "C0"], "SDS": ["00002090", ""]}, "toc": "NSC", "route": "00000", "direction": "S"}, {"prices": {"SDS": ["00001920", ""], "SVR": ["00002940", "4J"], "SDR": ["00003460", ""], "CDR": ["00001340", "TN"], "CDS": ["00001330", "TN"]}, "toc": "FCC", "route": "00028", "direction": "S"}], "5457": [{"prices": {"SDS": ["00001330", ""], "SVR": ["00002100", "4B"], "SDR": ["00002140", ""], "CDR": ["00001300", "B3"], "CDS": ["00001290", "B3"]}, "toc": "NSC", "route": "00000", "direction": "S"}], "5380": [{"prices": {"SDR": ["00001940", ""], "CDR": ["00001050", "C0"], "SDS": ["00000980", ""]}, "toc": "NSC", "route": "00000", "direction": "S"}], "5458": [{"prices": {"SDR": ["00002140", ""], "CDR": ["00001300", "B3"], "SDS": ["00001220", ""]}, "toc": "NSC", "route": "00000", "direction": "S"}], "3667": [{"prices": {"SDR": ["00004900", ""], "SDS": ["00003300", ""], "SOR": ["00006300", ""], "CDR": ["00003250", "C4"], "CDS": ["00003240", "C4"], "SVR": ["00003750", "4J"]}, "toc": "FCC", "route": "00000", "direction": "S"}], "5148": [{"prices": {"SDS": ["00001920", ""], "SVR": ["00002940", "4J"], "SDR": ["00003460", ""], "CDR": ["00001340", "TN"], "CDS": ["00001330", "TN"]}, "toc": "FCC", "route": "00028", "direction": "S"}], "0041": [{"prices": {"SVR": ["00002650", "4B"], "SDR": ["00003710", ""], "CDR": ["00001970", "C0"], "SDS": ["00001870", ""]}, "toc": "NSC", "route": "00000", "direction": "S"}], "0042": [{"prices": {"SVR": ["00002650", "4B"], "SDR": ["00003540", ""], "CDR": ["00001970", "C0"], "SDS": ["00001870", ""]}, "toc": "NSC", "route": "00000", "direction": "S"}], "0043": [{"prices": {"SVR": ["00002640", "4B"], "SDR": ["00003340", ""], "CDR": ["00001620", "C0"], "SDS": ["00001610", ""]}, "toc": "NSC", "route": "00000", "direction": "S"}], "0044": [{"prices": {"SVR": ["00002640", "4B"], "SDR": ["00003340", ""], "CDR": ["00001620", "C0"], "SDS": ["00001610", ""]}, "toc": "NSC", "route": "00000", "direction": "S"}], "5461": [{"prices": {"SDR": ["00002140", ""], "CDR": ["00001200", "B3"], "SDS": ["00001140", ""]}, "toc": "NSC", "route": "00000", "direction": "S"}], "5460": [{"prices": {"SDR": ["00002140", ""], "CDR": ["00001300", "B3"], "SDS": ["00001220", ""]}, "toc": "NSC", "route": "00000", "direction": "S"}], "5448": [{"prices": {"SDR": ["00002140", ""], "CDR": ["00001200", "B3"], "SDS": ["00001140", ""]}, "toc": "NSC", "route": "00000", "direction": "S"}], "K387": [{"prices": {"SDR": ["00004660", ""], "CDR": ["00002540", "TN"], "SDS": ["00002450", ""]}, "toc": "FCC", "route": "00028", "direction": "S"}], "5484": [{"prices": {"SDR": ["00001520", ""], "CDR": ["00000790", "B3"], "SDS": ["00000760", ""]}, "toc": "NSC", "route": "00000", "direction": "S"}], "5267": [{"prices": {"SDR": ["00001810", ""], "CDR": ["00001090", "B3"], "SDS": ["00001030", ""]}, "toc": "NSC", "route": "00000", "direction": "S"}], "0829": [{"prices": {"SDR": ["00003440", ""], "SDS": ["00001870", ""]}, "toc": "NSC", "route": "00598", "direction": "S"}, {"prices": {"SDR": ["00003550", ""], "SDS": ["00002060", ""]}, "toc": "NSC", "route": "00754", "direction": "S"}], "1555": [{"prices": {"SDS": ["00001920", ""], "SVR": ["00002940", "4J"], "SDR": ["00003460", ""], "CDR": ["00001340", "TN"], "CDS": ["00001330", "TN"]}, "toc": "FCC", "route": "00208", "direction": "S"}], "5260": [{"prices": {"SDR": ["00001810", ""], "CDR": ["00001290", "B3"], "SDS": ["00001210", ""]}, "toc": "NSC", "route": "00000", "direction": "S"}], "5365": [{"prices": {"SDR": ["00001640", ""], "CDR": ["00000860", "C0"], "SDS": ["00000820", ""]}, "toc": "NSC", "route": "00000", "direction": "S"}], "0072": [{"prices": {"SVR": ["00002650", "4B"], "SDR": ["00003340", ""], "CDR": ["00001620", "C0"], "SDS": ["00001610", ""]}, "toc": "NSC", "route": "00000", "direction": "S"}], "0577": [{"prices": {"SDS": ["00001920", ""], "SVR": ["00002940", "4J"], "SDR": ["00003460", ""], "CDR": ["00001340", "TN"], "CDS": ["00001330", "TN"]}, "toc": "FCC", "route": "00208", "direction": "S"}]}