{
  "0041": [
    {
      "prices": {
        "CDR": [
          "00004770",
          "US"
        ],
        "SDR": [
          "00007740",
          ""
        ],
        "SDS": [
          "00004030",
          ""
        ],
        "SOR": [
          "00008060",
          ""
        ],
        "SVR": [
          "00004780",
          "US"
        ]
      },
      "route": "00000",
      "toc": "SWT"
    }
  ],
  "0042": [
    {
      "prices": {
        "CDR": [
          "00004770",
          "UO"
        ],
        "SDR": [
          "00007740",
          ""
        ],
        "SDS": [
          "00004030",
          ""
        ],
        "SOR": [
          "00008060",
          ""
        ],
        "SVR": [
          "00004780",
          "UO"
        ]
      },
      "route": "00000",
      "toc": "SWT"
    }
  ],
  "0043": [
    {
      "prices": {
        "CDR": [
          "00004530",
          "UO"
        ],
        "SDR": [
          "00007180",
          ""
        ],
        "SDS": [
          "00003770",
          ""
        ],
        "SOR": [
          "00007540",
          ""
        ],
        "SVR": [
          "00004540",
          "UO"
        ]
      },
      "route": "00000",
      "toc": "SWT"
    }
  ],
  "0044": [
    {
      "prices": {
        "CDR": [
          "00004530",
          "UO"
        ],
        "SDR": [
          "00007180",
          ""
        ],
        "SDS": [
          "00003770",
          ""
        ],
        "SOR": [
          "00007540",
          ""
        ],
        "SVR": [
          "00004540",
          "UO"
        ]
      },
      "route": "00000",
      "toc": "SWT"
    }
  ],
  "0072": [
    {
      "prices": {
        "CDR": [
          "00004530",
          "UO"
        ],
        "SDR": [
          "00007180",
          ""
        ],
        "SDS": [
          "00003770",
          ""
        ],
        "SOR": [
          "00007540",
          ""
        ],
        "SVR": [
          "00004540",
          "UO"
        ]
      },
      "route": "00000",
      "toc": "SWT"
    }
  ],
  "1072": [
    {
      "prices": {
        "CDR": [
          "00005210",
          "US"
        ],
        "SDR": [
          "00009190",
          ""
        ],
        "SDS": [
          "00004650",
          ""
        ],
        "SOR": [
          "00009300",
          ""
        ],
        "SVR": [
          "00005270",
          "US"
        ]
      },
      "route": "00000",
      "toc": "SWT"
    }
  ],
  "1998": [
    {
      "prices": {
        "SOR": [
          "00002060",
          ""
        ],
        "SOS": [
          "00001030",
          ""
        ]
      },
      "route": "00000",
      "toc": "SWT"
    }
  ],
  "5836": [
    {
      "prices": {
        "CDR": [
          "00001230",
          "B3"
        ],
        "SDR": [
          "00001240",
          ""
        ],
        "SDS": [
          "00001170",
          ""
        ]
      },
      "route": "00000",
      "toc": "SWT"
    }
  ],
  "5875": [
    {
      "prices": {
        "CDR": [
          "00000890",
          "B3"
        ],
        "SDR": [
          "00000920",
          ""
        ],
        "SDS": [
          "00000860",
          ""
        ]
      },
      "route": "01000",
      "toc": "SWT"
    }
  ],
  "5876": [
    {
      "prices": {
        "CDR": [
          "00000870",
          "B3"
        ],
        "SDR": [
          "00000880",
          ""
        ],
        "SDS": [
          "00000860",
          ""
        ]
      },
      "route": "01000",
      "toc": "SWT"
    }
  ],
  "5879": [
    {
      "prices": {
        "CDR": [
          "00000770",
          "B3"
        ],
        "SDR": [
          "00000780",
          ""
        ],
        "SDS": [
          "00000730",
          ""
        ]
      },
      "route": "01000",
      "toc": "SWT"
    }
  ],
  "5880": [
    {
      "prices": {
        "CDR": [
          "00000670",
          "B3"
        ],
        "SDR": [
          "00000690",
          ""
        ],
        "SDS": [
          "00000640",
          ""
        ]
      },
      "route": "01000",
      "toc": "SWT"
    }
  ],
  "5881": [
    {
      "prices": {
        "CDR": [
          "00000590",
          "B3"
        ],
        "SDR": [
          "00000600",
          ""
        ],
        "SDS": [
          "00000510",
          ""
        ]
      },
      "route": "01000",
      "toc": "SWT"
    }
  ],
  "5884": [
    {
      "prices": {
        "CDR": [
          "00000470",
          "B3"
        ],
        "SDR": [
          "00000480",
          ""
        ],
        "SDS": [
          "00000450",
          ""
        ]
      },
      "route": "01000",
      "toc": "SWT"
    }
  ],
  "5885": [
    {
      "prices": {
        "CDR": [
          "00000860",
          "B3"
        ],
        "SDR": [
          "00000870",
          ""
        ],
        "SDS": [
          "00000850",
          ""
        ]
      },
      "route": "01000",
      "toc": "SWT"
    }
  ],
  "5886": [
    {
      "prices": {
        "CDR": [
          "00000410",
          "B3"
        ],
        "SDR": [
          "00000420",
          ""
        ],
        "SDS": [
          "00000360",
          ""
        ]
      },
      "route": "01000",
      "toc": "SWT"
    }
  ],
  "5887": [
    {
      "prices": {
        "CDR": [
          "00000280",
          "B3"
        ],
        "SDR": [
          "00000300",
          ""
        ],
        "SDS": [
          "00000230",
          ""
        ]
      },
      "route": "01000",
      "toc": "SWT"
    }
  ],
  "5890": [
    {
      "prices": {
        "CDR": [
          "00000590",
          "B3"
        ],
        "SDR": [
          "00000600",
          ""
        ],
        "SDS": [
          "00000510",
          ""
        ]
      },
      "route": "01000",
      "toc": "SWT"
    }
  ],
  "5894": [
    {
      "prices": {
        "CDR": [
          "00001420",
          "UQ"
        ],
        "SDR": [
          "00001460",
          ""
        ],
        "SDS": [
          "00001390",
          ""
        ]
      },
      "route": "01000",
      "toc": "SWT"
    }
  ],
  "5899": [
    {
      "prices": {
        "CDR": [
          "00001210",
          "UQ"
        ],
        "SDR": [
          "00001220",
          ""
        ],
        "SDS": [
          "00001130",
          ""
        ]
      },
      "route": "00000",
      "toc": "SWT"
    }
  ],
  "5900": [
    {
      "prices": {
        "CDR": [
          "00001510",
          "UQ"
        ],
        "SDR": [
          "00001520",
          ""
        ],
        "SDS": [
          "00001470",
          ""
        ]
      },
      "route": "01000",
      "toc": "SWT"
    }
  ],
  "5906": [
    {
      "prices": {
        "CDR": [
          "00000670",
          "UQ"
        ],
        "SDR": [
          "00000690",
          ""
        ],
        "SDS": [
          "00000640",
          ""
        ]
      },
      "route": "01000",
      "toc": "SWT"
    }
  ],
  "5909": [
    {
      "prices": {
        "CDR": [
          "00000860",
          "UQ"
        ],
        "SDR": [
          "00000870",
          ""
        ],
        "SDS": [
          "00000850",
          ""
        ]
      },
      "route": "01000",
      "toc": "SWT"
    }
  ],
  "5911": [
    {
      "prices": {
        "CDR": [
          "00001230",
          "UQ"
        ],
        "SDR": [
          "00001240",
          ""
        ],
        "SDS": [
          "00001170",
          ""
        ]
      },
      "route": "01000",
      "toc": "SWT"
    }
  ],
  "5912": [
    {
      "prices": {
        "CDR": [
          "00000770",
          "UQ"
        ],
        "SDR": [
          "00000780",
          ""
        ],
        "SDS": [
          "00000730",
          ""
        ]
      },
      "route": "01000",
      "toc": "SWT"
    }
  ],
  "5914": [
    {
      "prices": {
        "CDR": [
          "00001000",
          "UQ"
        ],
        "SDR": [
          "00001010",
          ""
        ],
        "SDS": [
          "00000920",
          ""
        ]
      },
      "route": "01000",
      "toc": "SWT"
    }
  ],
  "5920": [
    {
      "prices": {
        "CDR": [
          "00001420",
          "UQ"
        ],
        "SDR": [
          "00001460",
          ""
        ],
        "SDS": [
          "00001390",
          ""
        ]
      },
      "route": "01000",
      "toc": "SWT"
    }
  ],
  "5921": [
    {
      "prices": {
        "CDR": [
          "00000770",
          "UQ"
        ],
        "SDR": [
          "00000780",
          ""
        ],
        "SDS": [
          "00000730",
          ""
        ]
      },
      "route": "01000",
      "toc": "SWT"
    }
  ],
  "5922": [
    {
      "prices": {
        "CDR": [
          "00001210",
          "UQ"
        ],
        "SDR": [
          "00001220",
          ""
        ],
        "SDS": [
          "00001130",
          ""
        ]
      },
      "route": "01000",
      "toc": "SWT"
    }
  ],
  "5925": [
    {
      "prices": {
        "CDR": [
          "00001110",
          "UQ"
        ],
        "SDR": [
          "00001120",
          ""
        ],
        "SDS": [
          "00001060",
          ""
        ]
      },
      "route": "01000",
      "toc": "SWT"
    }
  ],
  "5927": [
    {
      "prices": {
        "CDR": [
          "00001310",
          "UQ"
        ],
        "SDR": [
          "00001320",
          ""
        ],
        "SDS": [
          "00001260",
          ""
        ]
      },
      "route": "01000",
      "toc": "SWT"
    }
  ],
  "5928": [
    {
      "prices": {
        "CDR": [
          "00001570",
          "UQ"
        ],
        "SDR": [
          "00001580",
          ""
        ],
        "SDS": [
          "00001520",
          ""
        ]
      },
      "route": "01000",
      "toc": "SWT"
    }
  ],
  "5930": [
    {
      "prices": {
        "CDR": [
          "00001150",
          "UQ"
        ],
        "SDR": [
          "00001170",
          ""
        ],
        "SDS": [
          "00001090",
          ""
        ]
      },
      "route": "01000",
      "toc": "SWT"
    }
  ],
  "5932": [
    {
      "prices": {
        "CDR": [
          "00000880",
          "UQ"
        ],
        "SDR": [
          "00000900",
          ""
        ],
        "SDS": [
          "00000860",
          ""
        ]
      },
      "route": "01000",
      "toc": "SWT"
    }
  ],
  "5933": [
    {
      "prices": {
        "CDR": [
          "00001060",
          "UQ"
        ],
        "SDR": [
          "00001080",
          ""
        ],
        "SDS": [
          "00001010",
          ""
        ]
      },
      "route": "01000",
      "toc": "SWT"
    }
  ],
  "5942": [
    {
      "prices": {
        "CDR": [
          "00001390",
          "UQ"
        ],
        "SDR": [
          "00001410",
          ""
        ],
        "SDS": [
          "00001320",
          ""
        ],
        "SOR": [
          "00002640",
          ""
        ],
        "SVR": [
          "00002590",
          "UQ"
        ]
      },
      "route": "00000",
      "toc": "SWT"
    }
  ],
  "5943": [
    {
      "prices": {
        "CDR": [
          "00001060",
          "UQ"
        ],
        "SDR": [
          "00001080",
          ""
        ],
        "SDS": [
          "00001010",
          ""
        ]
      },
      "route": "00000",
      "toc": "SWT"
    }
  ],
  "5944": [
    {
      "prices": {
        "CDR": [
          "00001210",
          "UQ"
        ],
        "SDR": [
          "00001220",
          ""
        ],
        "SDS": [
          "00001130",
          ""
        ]
      },
      "route": "00000",
      "toc": "SWT"
    }
  ],
  "5945": [
    {
      "prices": {
        "CDR": [
          "00001060",
          "UQ"
        ],
        "SDR": [
          "00001080",
          ""
        ],
        "SDS": [
          "00001010",
          ""
        ]
      },
      "route": "01000",
      "toc": "SWT"
    }
  ],
  "5947": [
    {
      "prices": {
        "CDR": [
          "00001230",
          "UQ"
        ],
        "SDR": [
          "00001240",
          ""
        ],
        "SDS": [
          "00001170",
          ""
        ]
      },
      "route": "01000",
      "toc": "SWT"
    }
  ],
  "5957": [
    {
      "prices": {
        "CDR": [
          "00001380",
          "UQ"
        ],
        "SDR": [
          "00001390",
          ""
        ],
        "SDS": [
          "00001260",
          ""
        ]
      },
      "route": "01000",
      "toc": "SWT"
    }
  ],
  "5960": [
    {
      "prices": {
        "CDR": [
          "00001380",
          "UQ"
        ],
        "SDR": [
          "00001390",
          ""
        ],
        "SDS": [
          "00001260",
          ""
        ]
      },
      "route": "01000",
      "toc": "SWT"
    }
  ],
  "7222": [
    {
      "prices": {
        "CDR": [
          "00006150",
          "US"
        ],
        "SDR": [
          "00010300",
          ""
        ],
        "SDS": [
          "00005270",
          ""
        ],
        "SVR": [
          "00006380",
          "US"
        ]
      },
      "route": "00000",
      "toc": "SWT"
    }
  ]
}