{"Q551": [{"prices": {"SOR": ["00010300", ""], "SVR": ["00008670", "8F"], "SDS": ["00008470", ""]}, "toc": "SCR", "route": "00000", "direction": "R"}, {"prices": {"SOR": ["00008630", ""], "SVR": ["00007290", "8F"], "SDS": ["00005880", ""]}, "toc": "SCR", "route": "00353", "direction": "R"}], "Q550": [{"prices": {"SOR": ["00009430", ""], "SVR": ["00007970", "8F"], "SDS": ["00008000", ""]}, "toc": "SCR", "route": "00000", "direction": "R"}, {"prices": {"SOR": ["00007780", ""], "SVR": ["00006590", "8F"], "SDS": ["00005440", ""]}, "toc": "SCR", "route": "00353", "direction": "R"}], "Q552": [{"prices": {"SDR": ["00002270", ""], "SDS": ["00001210", ""]}, "toc": "SCR", "route": "00000", "direction": "R"}], "Q559": [{"prices": {"SOR": ["00003240", ""], "SVR": ["00002730", "8F"], "SDS": ["00001760", ""]}, "toc": "SCR", "route": "00000", "direction": "R"}], "Q558": [{"prices": {"SOR": ["00002910", ""], "SVR": ["00002450", "8F"], "SDS": ["00001610", ""]}, "toc": "SCR", "route": "00000", "direction": "R"}], "Q101": [{"prices": {"SOS": ["00015950", ""], "SOR": ["00031900", ""], "SVR": ["00012250", "3A"]}, "toc": "IWC", "route": "00700", "direction": "S"}], "Q970": [{"prices": {"SOS": ["00017650", ""], "SOR": ["00035300", ""], "SVR": ["00019780", "2V"]}, "toc": "IXC", "route": "00000", "direction": "R"}], "Q537": [{"prices": {"SOR": ["00003950", ""], "SVR": ["00003330", "8F"], "SDS": ["00003030", ""]}, "toc": "SCR", "route": "00000", "direction": "R"}], "Q536": [{"prices": {"SOR": ["00005020", ""], "SVR": ["00004090", "8F"], "SDS": ["00002890", ""]}, "toc": "SCR", "route": "00000", "direction": "R"}], "Q535": [{"prices": {"SOR": ["00006640", ""], "SVR": ["00005610", "8F"], "SDS": ["00004500", ""]}, "toc": "SCR", "route": "00000", "direction": "R"}], "Q534": [{"prices": {"SOR": ["00005820", ""], "SVR": ["00004900", "8F"], "SDS": ["00004160", ""]}, "toc": "SCR", "route": "00000", "direction": "R"}], "Q533": [{"prices": {"SOR": ["00004110", ""], "SVR": ["00003550", "8F"], "SDS": ["00003100", ""]}, "toc": "SCR", "route": "00000", "direction": "R"}, {"prices": {"SOR": ["00003890", ""], "SVR": ["00003400", "8F"], "SDS": ["00002520", ""]}, "toc": "SCR", "route": "00352", "direction": "R"}], "Q532": [{"prices": {"SOR": ["00004500", ""], "SVR": ["00003930", "8F"], "SDS": ["00002570", ""]}, "toc": "SCR", "route": "00000", "direction": "R"}], "Q531": [{"prices": {"SOR": ["00004890", ""], "SVR": ["00004260", "8F"], "SDS": ["00002910", ""]}, "toc": "SCR", "route": "00000", "direction": "R"}], "Q530": [{"prices": {"SOR": ["00002490", ""], "SVR": ["00002090", "8F"], "SDS": ["00001380", ""]}, "toc": "SCR", "route": "00000", "direction": "R"}], "Q571": [{"prices": {"SOR": ["00003010", ""], "SVR": ["00002550", "8F"], "SDS": ["00002200", ""]}, "toc": "SCR", "route": "00000", "direction": "R"}], "Q570": [{"prices": {"SOR": ["00002650", ""], "SVR": ["00002220", "8F"], "SDS": ["00002020", ""]}, "toc": "SCR", "route": "00000", "direction": "R"}], "Q577": [{"prices": {"SOR": ["00002490", ""], "SVR": ["00002090", "8F"], "SDS": ["00001400", ""]}, "toc": "SCR", "route": "00000", "direction": "R"}], "Q562": [{"prices": {"SOR": ["00003760", ""], "SVR": ["00003180", "8F"], "SDS": ["00002030", ""]}, "toc": "SCR", "route": "00000", "direction": "R"}], "Q539": [{"prices": {"SOR": ["00009980", ""], "SVR": ["00008420", "8F"], "SDS": ["00005820", ""]}, "toc": "SCR", "route": "00000", "direction": "R"}], "Q538": [{"prices": {"SOR": ["00005350", ""], "SVR": ["00004740", "8F"], "SDS": ["00003470", ""]}, "toc": "SCR", "route": "00000", "direction": "R"}], "Q576": [{"prices": {"SOS": ["00017450", ""], "SOR": ["00034900", ""], "SVR": ["00019530", "2V"]}, "toc": "IXC", "route": "00700", "direction": "R"}], "Q575": [{"prices": {"SDS": ["00002030", ""], "SVR": ["00001980", "8F"], "SOR": ["00002140", ""], "CDR": ["00001950", "B7"], "CDS": ["00001940", "B7"]}, "toc": "SCR", "route": "00000", "direction": "R"}], "Q546": [{"prices": {"SOR": ["00008550", ""], "SVR": ["00007210", "8F"], "SDS": ["00007160", ""]}, "toc": "SCR", "route": "00000", "direction": "R"}, {"prices": {"SOR": ["00006870", ""], "SVR": ["00005810", "8F"], "SDS": ["00004620", ""]}, "toc": "SCR", "route": "00353", "direction": "R"}], "Q547": [{"prices": {"SOR": ["00008960", ""], "SVR": ["00007550", "8F"], "SDS": ["00007430", ""]}, "toc": "SCR", "route": "00000", "direction": "R"}, {"prices": {"SOR": ["00007300", ""], "SVR": ["00006160", "8F"], "SDS": ["00004880", ""]}, "toc": "SCR", "route": "00353", "direction": "R"}], "Q544": [{"prices": {"SOR": ["00007480", ""], "SVR": ["00006310", "8F"], "SDS": ["00006360", ""]}, "toc": "SCR", "route": "00000", "direction": "R"}, {"prices": {"SOR": ["00005540", ""], "SVR": ["00004900", "8F"], "SDS": ["00003780", ""]}, "toc": "SCR", "route": "00353", "direction": "R"}], "Q545": [{"prices": {"SOR": ["00008140", ""], "SVR": ["00006870", "8F"], "SDS": ["00006680", ""]}, "toc": "SCR", "route": "00000", "direction": "R"}, {"prices": {"SOR": ["00006450", ""], "SVR": ["00005440", "8F"], "SDS": ["00004210", ""]}, "toc": "SCR", "route": "00353", "direction": "R"}], "Q542": [{"prices": {"SOR": ["00010760", ""], "SVR": ["00009090", "8F"], "SDS": ["00006610", ""]}, "toc": "SCR", "route": "00000", "direction": "R"}], "Q543": [{"prices": {"SOR": ["00011020", ""], "SVR": ["00009310", "8F"], "SDS": ["00006810", ""]}, "toc": "SCR", "route": "00000", "direction": "R"}], "Q540": [{"prices": {"SOR": ["00010390", ""], "SVR": ["00008790", "8F"], "SDS": ["00006100", ""]}, "toc": "SCR", "route": "00000", "direction": "R"}], "Q541": [{"prices": {"SOR": ["00010620", ""], "SVR": ["00008960", "8F"], "SDS": ["00006270", ""]}, "toc": "SCR", "route": "00000", "direction": "R"}], "Q586": [], "Q548": [{"prices": {"SOR": ["00009640", ""], "SVR": ["00008130", "8F"], "SDS": ["00007710", ""]}, "toc": "SCR", "route": "00000", "direction": "R"}, {"prices": {"SOR": ["00008000", ""], "SVR": ["00006770", "8F"], "SDS": ["00005150", ""]}, "toc": "SCR", "route": "00353", "direction": "R"}], "Q549": [{"prices": {"SOR": ["00009860", ""], "SVR": ["00008320", "8F"], "SDS": ["00007780", ""]}, "toc": "SCR", "route": "00000", "direction": "R"}, {"prices": {"SOR": ["00008210", ""], "SVR": ["00006950", "8F"], "SDS": ["00005240", ""]}, "toc": "SCR", "route": "00353", "direction": "R"}], "Q111": [{"prices": {"SOS": ["00014300", ""], "SOR": ["00028600", ""], "SVR": ["00013160", "3A"]}, "toc": "IWC", "route": "00700", "direction": "S"}], "Q110": [{"prices": {"SOS": ["00014300", ""], "SOR": ["00028600", ""], "SVR": ["00013160", "3A"]}, "toc": "IWC", "route": "00202", "direction": "S"}, {"prices": {"SOS": ["00016500", ""], "SOR": ["00033000", ""], "SVR": ["00012230", "3A"]}, "toc": "IWC", "route": "00700", "direction": "S"}], "Q113": [{"prices": {"SOS": ["00015000", ""], "SOR": ["00030000", ""], "SVR": ["00013300", "3A"]}, "toc": "IWC", "route": "00700", "direction": "S"}], "Q560": [{"prices": {"SOR": ["00003340", ""], "SVR": ["00002820", "8F"], "SDS": ["00001870", ""]}, "toc": "SCR", "route": "00000", "direction": "R"}], "Q104": [{"prices": {"SOS": ["00015950", ""], "SOR": ["00031900", ""], "SVR": ["00012250", "3A"]}, "toc": "IWC", "route": "00700", "direction": "S"}], "Q563": [{"prices": {"SOR": ["00003820", ""], "SVR": ["00003240", "8F"], "SDS": ["00002130", ""]}, "toc": "SCR", "route": "00000", "direction": "R"}], "Q564": [{"prices": {"SOR": ["00003010", ""], "SVR": ["00002550", "8F"], "SDS": ["00002030", ""]}, "toc": "SCR", "route": "00000", "direction": "R"}], "Q565": [{"prices": {"SOR": ["00003430", ""], "SVR": ["00002890", "8F"], "SDS": ["00002100", ""]}, "toc": "SCR", "route": "00000", "direction": "R"}], "Q566": [{"prices": {"SOR": ["00003760", ""], "SVR": ["00003180", "8F"], "SDS": ["00002650", ""]}, "toc": "SCR", "route": "00000", "direction": "R"}], "Q567": [{"prices": {"SOR": ["00004030", ""], "SVR": ["00003420", "8F"], "SDS": ["00002940", ""]}, "toc": "SCR", "route": "00000", "direction": "R"}], "Q568": [{"prices": {"SOR": ["00006630", ""], "SVR": ["00005600", "8F"], "SDS": ["00004450", ""]}, "toc": "SCR", "route": "00000", "direction": "R"}], "J264": [{"prices": {"SOS": ["00013200", ""], "SOR": ["00026300", ""], "SVR": ["00013250", "2V"]}, "toc": "IXC", "route": "00000", "direction": "S"}], "Q569": [{"prices": {"SOR": ["00002490", ""], "SVR": ["00002090", "8F"], "SDS": ["00001920", ""]}, "toc": "SCR", "route": "00000", "direction": "R"}], "Q098": [{"prices": {"SOS": ["00014300", ""], "SOR": ["00028600", ""], "SVR": ["00013160", "3A"]}, "toc": "IWC", "route": "00700", "direction": "S"}], "H272": [{"prices": {"SOS": ["00013980", ""], "SOR": ["00027920", ""], "SVR": ["00014180", "8X"]}, "toc": "IXC", "route": "00000", "direction": "S"}], "Q578": [{"prices": {"SOR": ["00003020", ""], "SVR": ["00002560", "8F"], "SDS": ["00002100", ""]}, "toc": "SCR", "route": "00000", "direction": "R"}]}