{
  "6417": [
    {
      "prices": {
        "SOR": [
          "00019600",
          ""
        ],
        "SOS": [
          "00010250",
          ""
        ],
        "SSR": [
          "00008700",
          "HD"
        ],
        "SSS": [
          "00007650",
          "HD"
        ],
        "SVR": [
          "00014400",
          "HV"
        ],
        "SVS": [
          "00009750",
          "HV"
        ]
      },
      "route": "00595",
      "toc": "HUL"
    }
  ],
  "6511": [
    {
      "prices": {
        "SOR": [
          "00016450",
          ""
        ],
        "SOS": [
          "00009200",
          ""
        ],
        "SSR": [
          "00007600",
          "HD"
        ],
        "SSS": [
          "00006600",
          "HD"
        ],
        "SVR": [
          "00012350",
          "HV"
        ],
        "SVS": [
          "00007650",
          "HV"
        ]
      },
      "route": "00595",
      "toc": "HUL"
    }
  ],
  "QC34": [
    {
      "prices": {
        "SOR": [
          "00023550",
          ""
        ],
        "SOS": [
          "00012850",
          ""
        ],
        "SSR": [
          "00010550",
          "HD"
        ],
        "SSS": [
          "00009200",
          "HD"
        ],
        "SVR": [
          "00015950",
          "HV"
        ],
        "SVS": [
          "00012000",
          "HV"
        ]
      },
      "route": "00595",
      "toc": "HUL"
    }
  ]
}