{
  "6417": [
    {
      "prices": {
        "SOR": [
          "00025700",
          ""
        ],
        "SOS": [
          "00016700",
          ""
        ],
        "SSR": [
          "00013600",
          "HD"
        ],
        "SSS": [
          "00007300",
          "HD"
        ],
        "SVR": [
          "00018800",
          "HV"
        ],
        "SVS": [
          "00013100",
          "HV"
        ]
      },
      "route": "02015",
      "toc": "HUL"
    }
  ],
  "6469": [
    {
      "prices": {
        "SOR": [
          "00020900",
          "HS"
        ],
        "SOS": [
          "00013100",
          ""
        ],
        "SSR": [
          "00009400",
          "HD"
        ],
        "SSS": [
          "00005000",
          "HD"
        ],
        "SVR": [
          "00015200",
          "HV"
        ],
        "SVS": [
          "00010600",
          "HV"
        ]
      },
      "route": "02015",
      "toc": "HUL"
    }
  ],
  "6511": [
    {
      "prices": {
        "SOR": [
          "00023000",
          "HS"
        ],
        "SOS": [
          "00014600",
          ""
        ],
        "SSR": [
          "00012000",
          "HD"
        ],
        "SSS": [
          "00006700",
          "HD"
        ],
        "SVR": [
          "00017300",
          "HV"
        ],
        "SVS": [
          "00011700",
          "HV"
        ]
      },
      "route": "02015",
      "toc": "HUL"
    }
  ],
  "QC34": [
    {
      "prices": {
        "SOR": [
          "00027700",
          ""
        ],
        "SOS": [
          "00017600",
          ""
        ],
        "SSR": [
          "00016200",
          "HD"
        ],
        "SSS": [
          "00008600",
          "HD"
        ],
        "SVR": [
          "00021800",
          "HV"
        ],
        "SVS": [
          "00015500",
          "HV"
        ]
      },
      "route": "02015",
      "toc": "HUL"
    }
  ]
}