{"QZ05": [{"prices": {"SDR": ["00001700", ""], "SDS": ["00000940", ""]}, "toc": "ATO", "route": "00000"}], "QZ04": [{"prices": {"SDR": ["00001140", ""], "SDS": ["00000700", ""]}, "toc": "ATO", "route": "00000"}], "QZ07": [{"prices": {"SDR": ["00001140", ""], "SDS": ["00000700", ""]}, "toc": "ATO", "route": "00000"}], "7222": [{"prices": {"SDR": ["00001470", ""], "SDS": ["00000720", ""]}, "toc": "NSE", "route": "00208"}], "QZ01": [{"prices": {"SDR": ["00001600", ""], "SDS": ["00000800", ""]}, "toc": "ATO", "route": "00000"}], "QZ00": [{"prices": {"SDR": ["00001700", ""], "SDS": ["00000940", ""]}, "toc": "ATO", "route": "00000"}], "QZ03": [{"prices": {"SDR": ["00001140", ""], "SDS": ["00000700", ""]}, "toc": "ATO", "route": "00000"}], "QZ02": [{"prices": {"SDR": ["00001140", ""], "SDS": ["00000700", ""]}, "toc": "ATO", "route": "00000"}], "6085": [{"prices": {"SDR": ["00001420", ""], "CDR": ["00001190", "B1"], "SDS": ["00000930", ""]}, "toc": "FCC", "route": "00113"}], "6006": [{"prices": {"SDR": ["00001700", ""], "CDR": ["00001450", "B1"], "SDS": ["00001360", ""]}, "toc": "FCC", "route": "00000"}, {"prices": {"SDR": ["00001320", ""], "CDR": ["00001120", "B1"], "SDS": ["00000860", ""]}, "toc": "FCC", "route": "00113"}], "6008": [{"prices": {"SDR": ["00001700", ""], "CDR": ["00001450", "B1"], "SDS": ["00001360", ""]}, "toc": "FCC", "route": "00000"}, {"prices": {"SDR": ["00001070", ""], "CDR": ["00000860", "B1"], "SDS": ["00000650", ""]}, "toc": "FCC", "route": "00113"}], "QZ80": [{"prices": {"SDR": ["00000600", ""], "SDS": ["00000340", ""]}, "toc": "ATO", "route": "00700"}], "QZ82": [{"prices": {"SDR": ["00000500", ""], "SDS": ["00000280", ""]}, "toc": "ATO", "route": "00158"}], "QZ70": [{"prices": {"SDR": ["00001330", ""], "SDS": ["00000680", ""]}, "toc": "ATO", "route": "00208"}, {"prices": {"SDR": ["00000870", ""], "SDS": ["00000460", ""]}, "toc": "ATO", "route": "00700"}], "QZ71": [{"prices": {"SDR": ["00001600", ""], "SDS": ["00000800", ""]}, "toc": "ATO", "route": "00000"}, {"prices": {"SDR": ["00000730", ""], "SDS": ["00000400", ""]}, "toc": "ATO", "route": "00700"}], "QZ72": [{"prices": {"SDR": ["00001140", ""], "SDS": ["00000700", ""]}, "toc": "ATO", "route": "00000"}], "QZ73": [{"prices": {"SDR": ["00001140", ""], "SDS": ["00000700", ""]}, "toc": "ATO", "route": "00000"}, {"prices": {"SDR": ["00000600", ""], "SDS": ["00000340", ""]}, "toc": "ATO", "route": "00700"}], "QZ74": [{"prices": {"SDR": ["00000840", ""], "SDS": ["00000500", ""]}, "toc": "ATO", "route": "00208"}, {"prices": {"SDR": ["00000600", ""], "SDS": ["00000340", ""]}, "toc": "ATO", "route": "00600"}], "QZ75": [{"prices": {"SDR": ["00000580", ""], "SDS": ["00000310", ""]}, "toc": "ATO", "route": "00208"}, {"prices": {"SDR": ["00000390", ""], "SDS": ["00000210", ""]}, "toc": "ATO", "route": "00600"}], "7043": [{"prices": {"SVR": ["00003730", "4A"], "SDR": ["00003740", ""], "CDR": ["00002700", "B1"], "SDS": ["00002430", ""]}, "toc": "FCC", "route": "00000"}], "QZ79": [{"prices": {"SDR": ["00000390", ""], "SDS": ["00000210", ""]}, "toc": "ATO", "route": "00600"}], "6092": [{"prices": {"SDR": ["00002070", ""], "CDR": ["00001700", "B1"], "SDS": ["00001450", ""]}, "toc": "FCC", "route": "00113"}], "6095": [{"prices": {"SDR": ["00001610", ""], "CDR": ["00001360", "B1"], "SDS": ["00001150", ""]}, "toc": "FCC", "route": "00113"}], "6096": [{"prices": {"SDR": ["00001700", ""], "CDR": ["00001450", "B1"], "SDS": ["00001360", ""]}, "toc": "FCC", "route": "00000"}, {"prices": {"SDR": ["00001610", ""], "CDR": ["00001400", "B1"], "SDS": ["00001110", ""]}, "toc": "FCC", "route": "00113"}], "Q092": [{"prices": {"SVR": ["00003620", "4J"], "SDR": ["00002490", ""], "CDR": ["00002440", "LS"], "SDS": ["00002260", ""]}, "toc": "FCC", "route": "00000"}, {"prices": {"SDR": ["00002180", ""], "CDR": ["00001760", "B1"], "SDS": ["00001550", ""]}, "toc": "FCC", "route": "00113"}], "QZ06": [{"prices": {"SDR": ["00001600", ""], "SDS": ["00000800", ""]}, "toc": "ATO", "route": "00000"}], "6088": [{"prices": {"SDR": ["00001790", ""], "CDR": ["00001520", "B1"], "SDS": ["00001220", ""]}, "toc": "FCC", "route": "00113"}], "QZ63": [{"prices": {"SDR": ["00000900", ""], "SDS": ["00000570", ""]}, "toc": "ATO", "route": "00000"}], "QZ62": [{"prices": {"SDR": ["00000710", ""], "SDS": ["00000410", ""]}, "toc": "ATO", "route": "00208"}, {"prices": {"SDR": ["00000500", ""], "SDS": ["00000280", ""]}, "toc": "ATO", "route": "00600"}], "QZ61": [{"prices": {"SDR": ["00000840", ""], "SDS": ["00000500", ""]}, "toc": "ATO", "route": "00208"}, {"prices": {"SDR": ["00000600", ""], "SDS": ["00000340", ""]}, "toc": "ATO", "route": "00600"}], "QZ60": [{"prices": {"SDR": ["00000840", ""], "SDS": ["00000500", ""]}, "toc": "ATO", "route": "00208"}, {"prices": {"SDR": ["00000600", ""], "SDS": ["00000340", ""]}, "toc": "ATO", "route": "00600"}], "QZ67": [{"prices": {"SDR": ["00001600", ""], "SDS": ["00000800", ""]}, "toc": "ATO", "route": "00000"}, {"prices": {"SDR": ["00001080", ""], "SDS": ["00000590", ""]}, "toc": "ATO", "route": "00208"}, {"prices": {"SDR": ["00000730", ""], "SDS": ["00000400", ""]}, "toc": "ATO", "route": "00600"}], "QZ66": [{"prices": {"SDR": ["00001700", ""], "SDS": ["00000940", ""]}, "toc": "ATO", "route": "00000"}, {"prices": {"SDR": ["00001330", ""], "SDS": ["00000680", ""]}, "toc": "ATO", "route": "00208"}, {"prices": {"SDR": ["00000870", ""], "SDS": ["00000460", ""]}, "toc": "ATO", "route": "00600"}], "QZ65": [{"prices": {"SDR": ["00001330", ""], "SDS": ["00000680", ""]}, "toc": "ATO", "route": "00208"}, {"prices": {"SDR": ["00000870", ""], "SDS": ["00000460", ""]}, "toc": "ATO", "route": "00600"}], "QZ64": [{"prices": {"SDR": ["00001330", ""], "SDS": ["00000680", ""]}, "toc": "ATO", "route": "00208"}, {"prices": {"SDR": ["00000870", ""], "SDS": ["00000460", ""]}, "toc": "ATO", "route": "00600"}], "7038": [{"prices": {"SDS": ["00003230", ""], "SVR": ["00003850", "4A"], "SDR": ["00003800", ""], "CDR": ["00003090", "B1"], "CDS": ["00003080", "B1"]}, "toc": "FCC", "route": "00000"}], "QZ68": [{"prices": {"SDR": ["00001140", ""], "SDS": ["00000700", ""]}, "toc": "ATO", "route": "00000"}, {"prices": {"SDR": ["00000840", ""], "SDS": ["00000500", ""]}, "toc": "ATO", "route": "00208"}, {"prices": {"SDR": ["00000600", ""], "SDS": ["00000340", ""]}, "toc": "ATO", "route": "00600"}], "Q122": [{"prices": {"SVR": ["00003400", "4J"], "SDR": ["00002890", ""], "CDR": ["00002520", "LS"], "SDS": ["00002230", ""]}, "toc": "FCC", "route": "00000"}, {"prices": {"SDR": ["00002180", ""], "CDR": ["00001860", "B1"], "SDS": ["00001730", ""]}, "toc": "FCC", "route": "00113"}], "QZ46": [{"prices": {"SDR": ["00001330", ""], "SDS": ["00000680", ""]}, "toc": "ATO", "route": "00208"}], "7022": [{"prices": {"SVR": ["00003730", "4A"], "SDR": ["00003460", ""], "CDR": ["00002700", "B1"], "SDS": ["00002430", ""]}, "toc": "FCC", "route": "00000"}], "7027": [{"prices": {"SDS": ["00003170", ""], "SVR": ["00003680", "4A"], "SDR": ["00003800", ""], "CDR": ["00003090", "B1"], "CDS": ["00003080", "B1"]}, "toc": "FCC", "route": "00000"}], "QZ58": [{"prices": {"SDR": ["00001140", ""], "SDS": ["00000700", ""]}, "toc": "ATO", "route": "00000"}, {"prices": {"SDR": ["00000710", ""], "SDS": ["00000410", ""]}, "toc": "ATO", "route": "00208"}, {"prices": {"SDR": ["00000500", ""], "SDS": ["00000280", ""]}, "toc": "ATO", "route": "00600"}], "QZ59": [{"prices": {"SDR": ["00001080", ""], "SDS": ["00000590", ""]}, "toc": "ATO", "route": "00208"}, {"prices": {"SDR": ["00000730", ""], "SDS": ["00000400", ""]}, "toc": "ATO", "route": "00600"}], "QZ56": [{"prices": {"SDR": ["00001330", ""], "SDS": ["00000680", ""]}, "toc": "ATO", "route": "00208"}, {"prices": {"SDR": ["00000870", ""], "SDS": ["00000460", ""]}, "toc": "ATO", "route": "00600"}], "QZ57": [{"prices": {"SDR": ["00001080", ""], "SDS": ["00000590", ""]}, "toc": "ATO", "route": "00208"}, {"prices": {"SDR": ["00000730", ""], "SDS": ["00000400", ""]}, "toc": "ATO", "route": "00600"}], "QZ54": [{"prices": {"SDR": ["00000580", ""], "SDS": ["00000310", ""]}, "toc": "ATO", "route": "00208"}, {"prices": {"SDR": ["00000390", ""], "SDS": ["00000210", ""]}, "toc": "ATO", "route": "00600"}], "QZ55": [{"prices": {"SDR": ["00000710", ""], "SDS": ["00000410", ""]}, "toc": "ATO", "route": "00208"}, {"prices": {"SDR": ["00000500", ""], "SDS": ["00000280", ""]}, "toc": "ATO", "route": "00600"}], "QZ52": [{"prices": {"SDR": ["00000840", ""], "SDS": ["00000500", ""]}, "toc": "ATO", "route": "00208"}], "QZ53": [{"prices": {"SDR": ["00000580", ""], "SDS": ["00000310", ""]}, "toc": "ATO", "route": "00208"}], "QZ50": [{"prices": {"SDR": ["00000840", ""], "SDS": ["00000500", ""]}, "toc": "ATO", "route": "00208"}], "QZ51": [{"prices": {"SDR": ["00001080", ""], "SDS": ["00000590", ""]}, "toc": "ATO", "route": "00208"}], "6074": [{"prices": {"SDR": ["00001530", ""], "CDR": ["00001060", "B1"], "SDS": ["00001010", ""]}, "toc": "FCC", "route": "00000"}, {"prices": {"SDR": ["00001320", ""], "CDR": ["00001030", "B1"], "SDS": ["00000770", ""]}, "toc": "FCC", "route": "00113"}], "6073": [{"prices": {"SDR": ["00001530", ""], "CDR": ["00001060", "B1"], "SDS": ["00001010", ""]}, "toc": "FCC", "route": "00000"}, {"prices": {"SDR": ["00001320", ""], "CDR": ["00001030", "B1"], "SDS": ["00000820", ""]}, "toc": "FCC", "route": "00113"}], "6070": [{"prices": {"SDR": ["00001700", ""], "CDR": ["00001450", "B1"], "SDS": ["00001360", ""]}, "toc": "FCC", "route": "00000"}, {"prices": {"SDR": ["00001390", ""], "CDR": ["00001160", "B1"], "SDS": ["00000930", ""]}, "toc": "FCC", "route": "00113"}], "QZ49": [{"prices": {"SDR": ["00000840", ""], "SDS": ["00000500", ""]}, "toc": "ATO", "route": "00208"}, {"prices": {"SDR": ["00000600", ""], "SDS": ["00000340", ""]}, "toc": "ATO", "route": "00600"}], "QZ48": [{"prices": {"SDR": ["00000840", ""], "SDS": ["00000500", ""]}, "toc": "ATO", "route": "00208"}], "Q102": [{"prices": {"SVR": ["00003280", "4J"], "SDR": ["00002540", ""], "CDR": ["00002240", "LS"], "SDS": ["00001700", ""]}, "toc": "FCC", "route": "00000"}, {"prices": {"SDR": ["00002180", ""], "CDR": ["00001720", "B1"], "SDS": ["00001500", ""]}, "toc": "FCC", "route": "00113"}], "QZ41": [{"prices": {"SDR": ["00000710", ""], "SDS": ["00000410", ""]}, "toc": "ATO", "route": "00208"}], "QZ40": [{"prices": {"SDR": ["00000840", ""], "SDS": ["00000500", ""]}, "toc": "ATO", "route": "00208"}], "QZ43": [{"prices": {"SDR": ["00000710", ""], "SDS": ["00000410", ""]}, "toc": "ATO", "route": "00208"}], "QZ42": [{"prices": {"SDR": ["00000710", ""], "SDS": ["00000410", ""]}, "toc": "ATO", "route": "00208"}], "QZ45": [{"prices": {"SDR": ["00000580", ""], "SDS": ["00000310", ""]}, "toc": "ATO", "route": "00208"}], "QZ44": [{"prices": {"SDR": ["00000710", ""], "SDS": ["00000410", ""]}, "toc": "ATO", "route": "00208"}], "QZ47": [{"prices": {"SDR": ["00001080", ""], "SDS": ["00000590", ""]}, "toc": "ATO", "route": "00208"}], "Q109": [{"prices": {"SVR": ["00003280", "4J"], "SDR": ["00002380", ""], "CDR": ["00002130", "B1"], "SDS": ["00001700", ""]}, "toc": "FCC", "route": "00000"}], "Q119": [{"prices": {"SVR": ["00003730", "4J"], "SDR": ["00003280", ""], "CDR": ["00002810", "LS"], "SDS": ["00002530", ""]}, "toc": "FCC", "route": "00000"}, {"prices": {"SDR": ["00002630", ""], "CDR": ["00002330", "B1"], "SDS": ["00001900", ""]}, "toc": "FCC", "route": "00113"}], "5101": [{"prices": {"SDR": ["00001950", ""], "CDR": ["00001260", "C4"], "SDS": ["00001070", ""]}, "toc": "NSE", "route": "00208"}], "Q359": [{"prices": {"SVR": ["00004530", "4J"], "SDR": ["00004820", ""], "CDR": ["00003710", "LS"], "SDS": ["00003350", ""]}, "toc": "FCC", "route": "00000"}], "QZ38": [{"prices": {"SDR": ["00001330", ""], "SDS": ["00000680", ""]}, "toc": "ATO", "route": "00208"}], "QZ39": [{"prices": {"SDR": ["00001080", ""], "SDS": ["00000590", ""]}, "toc": "ATO", "route": "00208"}], "QZ34": [{"prices": {"SDR": ["00001700", ""], "SDS": ["00000940", ""]}, "toc": "ATO", "route": "00000"}], "QZ35": [{"prices": {"SDR": ["00001600", ""], "SDS": ["00000800", ""]}, "toc": "ATO", "route": "00000"}], "QZ36": [{"prices": {"SDR": ["00001140", ""], "SDS": ["00000700", ""]}, "toc": "ATO", "route": "00000"}], "QZ37": [{"prices": {"SDR": ["00000900", ""], "SDS": ["00000570", ""]}, "toc": "ATO", "route": "00000"}], "QZ30": [{"prices": {"SDR": ["00001700", ""], "SDS": ["00000940", ""]}, "toc": "ATO", "route": "00000"}, {"prices": {"SDR": ["00000870", ""], "SDS": ["00000460", ""]}, "toc": "ATO", "route": "00158"}], "QZ31": [{"prices": {"SDR": ["00001600", ""], "SDS": ["00000800", ""]}, "toc": "ATO", "route": "00000"}, {"prices": {"SDR": ["00000730", ""], "SDS": ["00000400", ""]}, "toc": "ATO", "route": "00158"}], "QZ32": [{"prices": {"SDR": ["00001140", ""], "SDS": ["00000700", ""]}, "toc": "ATO", "route": "00000"}, {"prices": {"SDR": ["00000600", ""], "SDS": ["00000340", ""]}, "toc": "ATO", "route": "00158"}], "QZ33": [{"prices": {"SDR": ["00001140", ""], "SDS": ["00000700", ""]}, "toc": "ATO", "route": "00000"}], "4452": [{"prices": {"SDR": ["00000580", ""], "SDS": ["00000310", ""]}, "toc": "ATO", "route": "00000"}], "7079": [{"prices": {"SVR": ["00003730", "4A"], "SDR": ["00003460", ""], "CDR": ["00002700", "B1"], "SDS": ["00002430", ""]}, "toc": "FCC", "route": "00000"}], "QZ29": [{"prices": {"SDR": ["00000900", ""], "SDS": ["00000570", ""]}, "toc": "ATO", "route": "00000"}], "QZ28": [{"prices": {"SDR": ["00001140", ""], "SDS": ["00000700", ""]}, "toc": "ATO", "route": "00000"}], "QZ27": [{"prices": {"SDR": ["00001140", ""], "SDS": ["00000700", ""]}, "toc": "ATO", "route": "00000"}], "QZ26": [{"prices": {"SDR": ["00001600", ""], "SDS": ["00000800", ""]}, "toc": "ATO", "route": "00000"}], "QZ25": [{"prices": {"SDR": ["00001700", ""], "SDS": ["00000940", ""]}, "toc": "ATO", "route": "00000"}], "QZ24": [{"prices": {"SDR": ["00001140", ""], "SDS": ["00000700", ""]}, "toc": "ATO", "route": "00000"}, {"prices": {"SDR": ["00000500", ""], "SDS": ["00000280", ""]}, "toc": "ATO", "route": "00113"}], "QZ23": [{"prices": {"SDR": ["00001140", ""], "SDS": ["00000700", ""]}, "toc": "ATO", "route": "00000"}, {"prices": {"SDR": ["00000600", ""], "SDS": ["00000340", ""]}, "toc": "ATO", "route": "00113"}], "QZ22": [{"prices": {"SDR": ["00001600", ""], "SDS": ["00000800", ""]}, "toc": "ATO", "route": "00000"}, {"prices": {"SDR": ["00000730", ""], "SDS": ["00000400", ""]}, "toc": "ATO", "route": "00113"}], "7072": [{"prices": {"SVR": ["00003960", "4A"], "SDR": ["00003970", ""], "CDR": ["00003250", "B1"], "SDS": ["00002940", ""]}, "toc": "FCC", "route": "00000"}], "QZ20": [{"prices": {"SDR": ["00000500", ""], "SDS": ["00000280", ""]}, "toc": "ATO", "route": "00000"}], "6183": [{"prices": {"SDR": ["00001700", ""], "CDR": ["00001450", "B1"], "SDS": ["00001360", ""]}, "toc": "FCC", "route": "00000"}, {"prices": {"SDR": ["00001550", ""], "CDR": ["00001340", "B1"], "SDS": ["00001000", ""]}, "toc": "FCC", "route": "00113"}], "6022": [{"prices": {"SDR": ["00001530", ""], "CDR": ["00001060", "B1"], "SDS": ["00001010", ""]}, "toc": "FCC", "route": "00000"}, {"prices": {"SDR": ["00001260", ""], "CDR": ["00000950", "B1"], "SDS": ["00000750", ""]}, "toc": "FCC", "route": "00113"}], "QZ21": [{"prices": {"SDR": ["00001700", ""], "SDS": ["00000940", ""]}, "toc": "ATO", "route": "00000"}, {"prices": {"SDR": ["00000870", ""], "SDS": ["00000460", ""]}, "toc": "ATO", "route": "00113"}], "0413": [{"prices": {"SDR": ["00001700", ""], "CDR": ["00001450", "B1"], "SDS": ["00001360", ""]}, "toc": "FCC", "route": "00000"}], "QZ18": [{"prices": {"SDR": ["00000870", ""], "SDS": ["00000460", ""]}, "toc": "ATO", "route": "00000"}], "QZ19": [{"prices": {"SDR": ["00000600", ""], "SDS": ["00000340", ""]}, "toc": "ATO", "route": "00000"}], "7068": [{"prices": {"SVR": ["00003850", "4A"], "SDR": ["00003690", ""], "CDR": ["00003140", "B1"], "SDS": ["00002720", ""]}, "toc": "FCC", "route": "00000"}], "QZ13": [{"prices": {"SDR": ["00001140", ""], "SDS": ["00000700", ""]}, "toc": "ATO", "route": "00000"}], "QZ16": [{"prices": {"SDR": ["00000900", ""], "SDS": ["00000570", ""]}, "toc": "ATO", "route": "00000"}], "QZ17": [{"prices": {"SDR": ["00001140", ""], "SDS": ["00000700", ""]}, "toc": "ATO", "route": "00000"}]}