{
  "H638": [
    {
      "prices": {
        "SOR": [
          "00043170",
          ""
        ],
        "SOS": [
          "00022570",
          ""
        ],
        "SSR": [
          "00021700",
          "9D"
        ],
        "SVR": [
          "00036040",
          "1T"
        ]
      },
      "route": "00000",
      "toc": "IEC"
    }
  ],
  "Q154": [
    {
      "prices": {
        "SOR": [
          "00045970",
          ""
        ],
        "SOS": [
          "00023910",
          ""
        ],
        "SSR": [
          "00020710",
          "9D"
        ],
        "SSS": [
          "00020600",
          "9D"
        ],
        "SVR": [
          "00035540",
          "1T"
        ]
      },
      "route": "00000",
      "toc": "IEC"
    }
  ],
  "Q156": [
    {
      "prices": {
        "SOR": [
          "00050380",
          ""
        ],
        "SOS": [
          "00025190",
          ""
        ],
        "SVR": [
          "00019790",
          "5F"
        ],
        "SVS": [
          "00013850",
          "5F"
        ]
      },
      "route": "00200",
      "toc": "IWC"
    }
  ],
  "Q159": [
    {
      "prices": {
        "SOR": [
          "00050380",
          ""
        ],
        "SOS": [
          "00025190",
          ""
        ],
        "SVR": [
          "00017710",
          "5F"
        ],
        "SVS": [
          "00012390",
          "5F"
        ]
      },
      "route": "00200",
      "toc": "IWC"
    }
  ],
  "Q163": [
    {
      "prices": {
        "SOR": [
          "00050380",
          ""
        ],
        "SOS": [
          "00025190",
          ""
        ],
        "SVR": [
          "00018340",
          "5F"
        ],
        "SVS": [
          "00012830",
          "5F"
        ]
      },
      "route": "00200",
      "toc": "IWC"
    }
  ],
  "Q164": [
    {
      "prices": {
        "SOR": [
          "00050380",
          ""
        ],
        "SOS": [
          "00025190",
          ""
        ],
        "SVR": [
          "00018150",
          "5F"
        ],
        "SVS": [
          "00012700",
          "5F"
        ]
      },
      "route": "00200",
      "toc": "IWC"
    }
  ],
  "Q165": [
    {
      "prices": {
        "SOR": [
          "00050380",
          ""
        ],
        "SOS": [
          "00025190",
          ""
        ],
        "SVR": [
          "00019790",
          "5F"
        ],
        "SVS": [
          "00013850",
          "5F"
        ]
      },
      "route": "00200",
      "toc": "IWC"
    }
  ],
  "Q166": [
    {
      "prices": {
        "SOR": [
          "00050380",
          ""
        ],
        "SOS": [
          "00025190",
          ""
        ],
        "SVR": [
          "00020420",
          "5F"
        ],
        "SVS": [
          "00014290",
          "5F"
        ]
      },
      "route": "00200",
      "toc": "IWC"
    }
  ],
  "Q177": [
    {
      "prices": {
        "SOR": [
          "00031030",
          ""
        ],
        "SOS": [
          "00016140",
          ""
        ],
        "SSR": [
          "00013510",
          "9D"
        ],
        "SSS": [
          "00013400",
          "9D"
        ],
        "SVR": [
          "00023210",
          "1T"
        ]
      },
      "route": "00000",
      "toc": "IEC"
    }
  ],
  "Q181": [
    {
      "prices": {
        "SOR": [
          "00033260",
          ""
        ],
        "SOS": [
          "00017300",
          ""
        ],
        "SSR": [
          "00015260",
          "9D"
        ],
        "SSS": [
          "00015140",
          "9D"
        ],
        "SVR": [
          "00025290",
          "1T"
        ]
      },
      "route": "00000",
      "toc": "IEC"
    }
  ],
  "Q270": [
    {
      "prices": {
        "SOR": [
          "00040040",
          ""
        ],
        "SOS": [
          "00020830",
          ""
        ],
        "SSR": [
          "00019520",
          "9D"
        ],
        "SVR": [
          "00031340",
          "1T"
        ]
      },
      "route": "00000",
      "toc": "IEC"
    }
  ],
  "Q274": [
    {
      "prices": {
        "SOR": [
          "00037920",
          ""
        ],
        "SOS": [
          "00019720",
          ""
        ],
        "SSR": [
          "00018150",
          "9D"
        ],
        "SSS": [
          "00018030",
          "9D"
        ],
        "SVR": [
          "00029670",
          "1T"
        ]
      },
      "route": "00000",
      "toc": "IEC"
    }
  ],
  "Q342": [
    {
      "prices": {
        "SOR": [
          "00030560",
          ""
        ],
        "SOS": [
          "00015280",
          ""
        ],
        "SSR": [
          "00012850",
          "9D"
        ],
        "SSS": [
          "00012390",
          "9D"
        ],
        "SVR": [
          "00020850",
          "1T"
        ]
      },
      "route": "00000",
      "toc": "SMR"
    }
  ],
  "Q346": [
    {
      "prices": {
        "SOR": [
          "00029760",
          ""
        ],
        "SOS": [
          "00015480",
          ""
        ],
        "SSR": [
          "00013510",
          "9D"
        ],
        "SSS": [
          "00013400",
          "9D"
        ],
        "SVR": [
          "00022850",
          "1T"
        ]
      },
      "route": "00000",
      "toc": "IEC"
    }
  ],
  "Q347": [
    {
      "prices": {
        "SOR": [
          "00031560",
          ""
        ],
        "SOS": [
          "00016420",
          ""
        ],
        "SSR": [
          "00014300",
          "9D"
        ],
        "SSS": [
          "00014190",
          "9D"
        ],
        "SVR": [
          "00024280",
          "1T"
        ]
      },
      "route": "00200",
      "toc": "IEC"
    }
  ],
  "Q348": [
    {
      "prices": {
        "SOR": [
          "00028490",
          ""
        ],
        "SOS": [
          "00014820",
          ""
        ],
        "SSR": [
          "00012070",
          "9D"
        ],
        "SSS": [
          "00011960",
          "9D"
        ],
        "SVR": [
          "00020860",
          "1T"
        ]
      },
      "route": "00000",
      "toc": "IEC"
    }
  ],
  "Q349": [
    {
      "prices": {
        "SOR": [
          "00031460",
          ""
        ],
        "SOS": [
          "00016970",
          ""
        ],
        "SSR": [
          "00014480",
          "9D"
        ],
        "SSS": [
          "00014370",
          "9D"
        ],
        "SVR": [
          "00024880",
          "1T"
        ]
      },
      "route": "00000",
      "toc": "IEC"
    }
  ],
  "Q350": [
    {
      "prices": {
        "SOR": [
          "00029340",
          ""
        ],
        "SOS": [
          "00015260",
          ""
        ],
        "SSR": [
          "00013310",
          "9D"
        ],
        "SSS": [
          "00013210",
          "9D"
        ],
        "SVR": [
          "00022550",
          "1T"
        ]
      },
      "route": "00200",
      "toc": "IEC"
    }
  ],
  "Q370": [
    {
      "prices": {
        "SOR": [
          "00043740",
          ""
        ],
        "SOS": [
          "00022800",
          ""
        ],
        "SSR": [
          "00021690",
          "9F"
        ],
        "SVR": [
          "00036430",
          "1V"
        ]
      },
      "route": "00000",
      "toc": "IEC"
    }
  ],
  "Q371": [
    {
      "prices": {
        "SOR": [
          "00047200",
          ""
        ],
        "SOS": [
          "00023600",
          ""
        ],
        "SVR": [
          "00020690",
          "2C"
        ],
        "SVS": [
          "00014480",
          "2C"
        ]
      },
      "route": "00275",
      "toc": "IWC"
    }
  ],
  "Q479": [
    {
      "prices": {
        "SOR": [
          "00044590",
          ""
        ],
        "SOS": [
          "00023240",
          ""
        ],
        "SSR": [
          "00019710",
          "9D"
        ],
        "SSS": [
          "00019600",
          "9D"
        ],
        "SVR": [
          "00034100",
          "1T"
        ]
      },
      "route": "00000",
      "toc": "IEC"
    }
  ],
  "Q482": [
    {
      "prices": {
        "SOR": [
          "00041520",
          ""
        ],
        "SOS": [
          "00021600",
          ""
        ],
        "SSR": [
          "00018610",
          "9D"
        ],
        "SSS": [
          "00018500",
          "9D"
        ],
        "SVR": [
          "00031580",
          "1T"
        ]
      },
      "route": "00064",
      "toc": "IEC"
    }
  ],
  "Q670": [
    {
      "prices": {
        "SOR": [
          "00043330",
          ""
        ],
        "SOS": [
          "00022650",
          ""
        ],
        "SSR": [
          "00021860",
          "9D"
        ],
        "SVR": [
          "00036200",
          "1T"
        ]
      },
      "route": "00000",
      "toc": "IEC"
    }
  ],
  "R607": [
    {
      "prices": {
        "SOR": [
          "00027330",
          ""
        ],
        "SOS": [
          "00014710",
          ""
        ],
        "SSR": [
          "00012080",
          "9D"
        ],
        "SSS": [
          "00011970",
          "9D"
        ],
        "SVR": [
          "00019740",
          "1T"
        ]
      },
      "route": "00000",
      "toc": "IEC"
    }
  ],
  "R608": [
    {
      "prices": {
        "SOR": [
          "00026590",
          ""
        ],
        "SOS": [
          "00013830",
          ""
        ],
        "SSR": [
          "00010710",
          "9D"
        ],
        "SSS": [
          "00010600",
          "9D"
        ],
        "SVR": [
          "00018240",
          "1T"
        ]
      },
      "route": "00000",
      "toc": "IEC"
    }
  ],
  "R629": [
    {
      "prices": {
        "SOR": [
          "00039400",
          ""
        ],
        "SOS": [
          "00020490",
          ""
        ],
        "SSR": [
          "00018280",
          "9D"
        ],
        "SSS": [
          "00018170",
          "9D"
        ],
        "SVR": [
          "00030380",
          "1T"
        ]
      },
      "route": "00000",
      "toc": "IEC"
    }
  ],
  "R631": [
    {
      "prices": {
        "SOR": [
          "00041520",
          ""
        ],
        "SOS": [
          "00021600",
          ""
        ],
        "SSR": [
          "00019050",
          "9D"
        ],
        "SSS": [
          "00018930",
          "9D"
        ],
        "SVR": [
          "00032060",
          "1T"
        ]
      },
      "route": "00000",
      "toc": "IEC"
    }
  ],
  "R635": [
    {
      "prices": {
        "SOR": [
          "00036650",
          ""
        ],
        "SOS": [
          "00019060",
          ""
        ],
        "SSR": [
          "00016410",
          "9D"
        ],
        "SSS": [
          "00016310",
          "9D"
        ],
        "SVR": [
          "00028000",
          "1T"
        ]
      },
      "route": "00000",
      "toc": "IEC"
    }
  ],
  "R641": [
    {
      "prices": {
        "SOR": [
          "00040460",
          ""
        ],
        "SOS": [
          "00021040",
          ""
        ],
        "SSR": [
          "00018480",
          "9D"
        ],
        "SSS": [
          "00018360",
          "9D"
        ],
        "SVR": [
          "00030870",
          "1T"
        ]
      },
      "route": "00000",
      "toc": "IEC"
    }
  ],
  "R642": [
    {
      "prices": {
        "SOR": [
          "00041520",
          ""
        ],
        "SOS": [
          "00021600",
          ""
        ],
        "SSR": [
          "00018610",
          "9D"
        ],
        "SSS": [
          "00018500",
          "9D"
        ],
        "SVR": [
          "00031580",
          "1T"
        ]
      },
      "route": "00000",
      "toc": "IEC"
    }
  ],
  "R652": [
    {
      "prices": {
        "SOR": [
          "00042890",
          ""
        ],
        "SOS": [
          "00022360",
          ""
        ],
        "SSR": [
          "00021420",
          "9D"
        ],
        "SVR": [
          "00035760",
          "1T"
        ]
      },
      "route": "00000",
      "toc": "IEC"
    }
  ],
  "R653": [
    {
      "prices": {
        "SOR": [
          "00043320",
          ""
        ],
        "SOS": [
          "00022580",
          ""
        ],
        "SSR": [
          "00021540",
          "9D"
        ],
        "SVR": [
          "00035950",
          "1T"
        ]
      },
      "route": "00000",
      "toc": "IEC"
    }
  ],
  "R655": [
    {
      "prices": {
        "SOR": [
          "00039400",
          ""
        ],
        "SOS": [
          "00020490",
          ""
        ],
        "SSR": [
          "00018530",
          "9D"
        ],
        "SSS": [
          "00018430",
          "9D"
        ],
        "SVR": [
          "00030380",
          "1T"
        ]
      },
      "route": "00000",
      "toc": "IEC"
    }
  ],
  "R656": [
    {
      "prices": {
        "SOR": [
          "00042890",
          ""
        ],
        "SOS": [
          "00022360",
          ""
        ],
        "SSR": [
          "00021100",
          "9D"
        ],
        "SVR": [
          "00035650",
          "1T"
        ]
      },
      "route": "00000",
      "toc": "IEC"
    }
  ],
  "R657": [
    {
      "prices": {
        "SOR": [
          "00042470",
          ""
        ],
        "SOS": [
          "00022140",
          ""
        ],
        "SSR": [
          "00020500",
          "9D"
        ],
        "SSS": [
          "00020390",
          "9D"
        ],
        "SVR": [
          "00034750",
          "1T"
        ]
      },
      "route": "00000",
      "toc": "IEC"
    }
  ],
  "R662": [
    {
      "prices": {
        "SOR": [
          "00043110",
          ""
        ],
        "SOS": [
          "00022470",
          ""
        ],
        "SSR": [
          "00019050",
          "9D"
        ],
        "SSS": [
          "00018930",
          "9D"
        ],
        "SVR": [
          "00032550",
          "1T"
        ]
      },
      "route": "00000",
      "toc": "IEC"
    }
  ],
  "R664": [
    {
      "prices": {
        "SOR": [
          "00042680",
          ""
        ],
        "SOS": [
          "00022250",
          ""
        ],
        "SSR": [
          "00019000",
          "9D"
        ],
        "SSS": [
          "00018880",
          "9D"
        ],
        "SVR": [
          "00032120",
          "1T"
        ]
      },
      "route": "00053",
      "toc": "IEC"
    }
  ],
  "R665": [
    {
      "prices": {
        "SOR": [
          "00037070",
          ""
        ],
        "SOS": [
          "00019280",
          ""
        ],
        "SSR": [
          "00016650",
          "9D"
        ],
        "SSS": [
          "00016530",
          "9D"
        ],
        "SVR": [
          "00028750",
          "1T"
        ]
      },
      "route": "00000",
      "toc": "IEC"
    }
  ],
  "R674": [
    {
      "prices": {
        "SOR": [
          "00042050",
          ""
        ],
        "SOS": [
          "00021920",
          ""
        ],
        "SSR": [
          "00019710",
          "9D"
        ],
        "SSS": [
          "00019600",
          "9D"
        ],
        "SVR": [
          "00033250",
          "1T"
        ]
      },
      "route": "00000",
      "toc": "IEC"
    }
  ],
  "R901": [
    {
      "prices": {
        "SOR": [
          "00049570",
          ""
        ],
        "SOS": [
          "00025780",
          ""
        ],
        "SSR": [
          "00024410",
          "9F"
        ],
        "SVR": [
          "00041390",
          "1V"
        ]
      },
      "route": "00000",
      "toc": "IEC"
    }
  ],
  "R902": [
    {
      "prices": {
        "SOR": [
          "00050840",
          ""
        ],
        "SOS": [
          "00026440",
          ""
        ],
        "SSR": [
          "00025200",
          "9F"
        ],
        "SVR": [
          "00042580",
          "1V"
        ]
      },
      "route": "00000",
      "toc": "IEC"
    }
  ],
  "R903": [
    {
      "prices": {
        "SOR": [
          "00053170",
          ""
        ],
        "SOS": [
          "00027650",
          ""
        ],
        "SSR": [
          "00026570",
          "9F"
        ],
        "SVR": [
          "00044370",
          "1V"
        ]
      },
      "route": "00000",
      "toc": "IEC"
    }
  ],
  "R905": [
    {
      "prices": {
        "SOR": [
          "00048930",
          ""
        ],
        "SOS": [
          "00025450",
          ""
        ],
        "SSR": [
          "00024290",
          "9F"
        ],
        "SVR": [
          "00041230",
          "1V"
        ]
      },
      "route": "00000",
      "toc": "IEC"
    }
  ],
  "R907": [
    {
      "prices": {
        "SOR": [
          "00047660",
          ""
        ],
        "SOS": [
          "00024790",
          ""
        ],
        "SSR": [
          "00023450",
          "9F"
        ],
        "SVR": [
          "00039950",
          "1V"
        ]
      },
      "route": "00000",
      "toc": "IEC"
    }
  ],
  "R908": [
    {
      "prices": {
        "SOR": [
          "00046390",
          ""
        ],
        "SOS": [
          "00024130",
          ""
        ],
        "SSR": [
          "00022790",
          "9F"
        ],
        "SVR": [
          "00038890",
          "1V"
        ]
      },
      "route": "00000",
      "toc": "IEC"
    }
  ],
  "R909": [
    {
      "prices": {
        "SOR": [
          "00044170",
          ""
        ],
        "SOS": [
          "00023020",
          ""
        ],
        "SSR": [
          "00022260",
          "9F"
        ],
        "SVR": [
          "00038170",
          "1V"
        ]
      },
      "route": "00000",
      "toc": "IEC"
    }
  ],
  "R910": [
    {
      "prices": {
        "SOR": [
          "00049860",
          ""
        ],
        "SOS": [
          "00024930",
          ""
        ],
        "SVR": [
          "00026060",
          "5F"
        ],
        "SVS": [
          "00018240",
          "5F"
        ]
      },
      "route": "00000",
      "toc": "IWC"
    }
  ],
  "R911": [
    {
      "prices": {
        "SOR": [
          "00049860",
          ""
        ],
        "SOS": [
          "00024930",
          ""
        ],
        "SVR": [
          "00025000",
          "5F"
        ],
        "SVS": [
          "00017500",
          "5F"
        ]
      },
      "route": "00000",
      "toc": "IWC"
    }
  ],
  "R912": [
    {
      "prices": {
        "SOR": [
          "00049860",
          ""
        ],
        "SOS": [
          "00024930",
          ""
        ],
        "SVR": [
          "00024920",
          "5F"
        ],
        "SVS": [
          "00017440",
          "5F"
        ]
      },
      "route": "00000",
      "toc": "IWC"
    }
  ],
  "R913": [
    {
      "prices": {
        "SOR": [
          "00049860",
          ""
        ],
        "SOS": [
          "00024930",
          ""
        ],
        "SVR": [
          "00023340",
          "5F"
        ],
        "SVS": [
          "00016330",
          "5F"
        ]
      },
      "route": "00000",
      "toc": "IWC"
    }
  ],
  "R914": [
    {
      "prices": {
        "SOR": [
          "00049860",
          ""
        ],
        "SOS": [
          "00024930",
          ""
        ],
        "SVR": [
          "00023950",
          "5F"
        ],
        "SVS": [
          "00016760",
          "5F"
        ]
      },
      "route": "00000",
      "toc": "IWC"
    },
    {
      "prices": {
        "SOR": [
          "00049860",
          ""
        ],
        "SOS": [
          "00024930",
          ""
        ],
        "SVR": [
          "00022840",
          "3A"
        ],
        "SVS": [
          "00015980",
          "3A"
        ]
      },
      "route": "00093",
      "toc": "IWC"
    }
  ],
  "R915": [
    {
      "prices": {
        "SOR": [
          "00049860",
          ""
        ],
        "SOS": [
          "00024930",
          ""
        ],
        "SVR": [
          "00019480",
          "5F"
        ],
        "SVS": [
          "00013630",
          "5F"
        ]
      },
      "route": "00000",
      "toc": "IWC"
    }
  ],
  "R920": [
    {
      "prices": {
        "SOR": [
          "00043950",
          ""
        ],
        "SOS": [
          "00022910",
          ""
        ],
        "SSR": [
          "00021800",
          "9F"
        ],
        "SVR": [
          "00036430",
          "1V"
        ]
      },
      "route": "00000",
      "toc": "IEC"
    }
  ],
  "R921": [
    {
      "prices": {
        "SOR": [
          "00043950",
          ""
        ],
        "SOS": [
          "00022910",
          ""
        ],
        "SSR": [
          "00021800",
          "9F"
        ],
        "SVR": [
          "00036430",
          "1V"
        ]
      },
      "route": "00000",
      "toc": "IEC"
    }
  ],
  "R925": [
    {
      "prices": {
        "SOR": [
          "00049860",
          ""
        ],
        "SOS": [
          "00024930",
          ""
        ],
        "SVR": [
          "00022220",
          "5F"
        ],
        "SVS": [
          "00015550",
          "5F"
        ]
      },
      "route": "00000",
      "toc": "IWC"
    }
  ],
  "R926": [
    {
      "prices": {
        "SOR": [
          "00049860",
          ""
        ],
        "SOS": [
          "00024930",
          ""
        ],
        "SVR": [
          "00022610",
          "5F"
        ],
        "SVS": [
          "00015820",
          "5F"
        ]
      },
      "route": "00000",
      "toc": "IWC"
    }
  ],
  "R928": [
    {
      "prices": {
        "SOR": [
          "00049860",
          ""
        ],
        "SOS": [
          "00024930",
          ""
        ],
        "SVR": [
          "00023280",
          "5F"
        ],
        "SVS": [
          "00016290",
          "5F"
        ]
      },
      "route": "00000",
      "toc": "IWC"
    }
  ]
}