{
  "H638": [
    {
      "prices": {
        "SOS": [
          "00012790",
          ""
        ],
        "SVS": [
          "00009940",
          "3V"
        ]
      },
      "route": "00700",
      "toc": "IEC"
    }
  ],
  "Q154": [
    {
      "prices": {
        "SOS": [
          "00012170",
          ""
        ],
        "SVS": [
          "00009050",
          "3V"
        ]
      },
      "route": "00700",
      "toc": "IEC"
    }
  ],
  "Q177": [
    {
      "prices": {
        "SDS": [
          "00006580",
          ""
        ],
        "SVS": [
          "00004720",
          "3V"
        ]
      },
      "route": "00700",
      "toc": "IEC"
    }
  ],
  "Q181": [
    {
      "prices": {
        "SDS": [
          "00007300",
          ""
        ],
        "SVS": [
          "00005280",
          "3V"
        ]
      },
      "route": "00700",
      "toc": "IEC"
    }
  ],
  "Q270": [
    {
      "prices": {
        "SOS": [
          "00010830",
          ""
        ],
        "SVS": [
          "00007860",
          "3V"
        ]
      },
      "route": "00700",
      "toc": "IEC"
    }
  ],
  "Q274": [
    {
      "prices": {
        "SOS": [
          "00009370",
          ""
        ],
        "SVS": [
          "00006890",
          "3V"
        ]
      },
      "route": "00700",
      "toc": "IEC"
    }
  ],
  "Q278": [
    {
      "prices": {
        "SOS": [
          "00011410",
          ""
        ],
        "SVS": [
          "00008580",
          "3V"
        ]
      },
      "route": "00700",
      "toc": "IEC"
    }
  ],
  "Q370": [
    {
      "prices": {
        "SOS": [
          "00012870",
          ""
        ],
        "SVS": [
          "00010030",
          "3V"
        ]
      },
      "route": "00700",
      "toc": "IEC"
    }
  ],
  "Q466": [
    {
      "prices": {
        "SOS": [
          "00010190",
          ""
        ],
        "SVS": [
          "00007610",
          "3V"
        ]
      },
      "route": "00700",
      "toc": "IEC"
    }
  ],
  "Q469": [
    {
      "prices": {
        "SDS": [
          "00008640",
          ""
        ],
        "SVS": [
          "00006170",
          "3V"
        ]
      },
      "route": "00700",
      "toc": "IEC"
    }
  ],
  "Q479": [
    {
      "prices": {
        "SOS": [
          "00011180",
          ""
        ],
        "SVS": [
          "00008290",
          "3V"
        ]
      },
      "route": "00700",
      "toc": "IEC"
    }
  ],
  "Q482": [
    {
      "prices": {
        "SOS": [
          "00010420",
          ""
        ],
        "SVS": [
          "00007890",
          "3V"
        ]
      },
      "route": "00700",
      "toc": "IEC"
    }
  ],
  "Q484": [
    {
      "prices": {
        "SOS": [
          "00010190",
          ""
        ],
        "SVS": [
          "00007610",
          "3V"
        ]
      },
      "route": "00700",
      "toc": "IEC"
    }
  ],
  "Q565": [
    {
      "prices": {
        "SOS": [
          "00013680",
          ""
        ],
        "SVS": [
          "00010940",
          "3V"
        ]
      },
      "route": "00700",
      "toc": "IEC"
    }
  ],
  "Q568": [
    {
      "prices": {
        "SOS": [
          "00015890",
          ""
        ],
        "SVS": [
          "00012590",
          "3V"
        ]
      },
      "route": "00700",
      "toc": "IEC"
    }
  ],
  "Q670": [
    {
      "prices": {
        "SOS": [
          "00012890",
          ""
        ],
        "SVS": [
          "00010040",
          "3V"
        ]
      },
      "route": "00700",
      "toc": "IEC"
    }
  ],
  "QN04": [
    {
      "prices": {
        "SOS": [
          "00012810",
          ""
        ],
        "SVS": [
          "00009920",
          "3V"
        ]
      },
      "route": "00700",
      "toc": "IEC"
    }
  ],
  "R629": [
    {
      "prices": {
        "SOS": [
          "00010190",
          ""
        ],
        "SVS": [
          "00007610",
          "3V"
        ]
      },
      "route": "00700",
      "toc": "IEC"
    }
  ],
  "R631": [
    {
      "prices": {
        "SOS": [
          "00010950",
          ""
        ],
        "SVS": [
          "00008010",
          "3V"
        ]
      },
      "route": "00700",
      "toc": "IEC"
    }
  ],
  "R641": [
    {
      "prices": {
        "SOS": [
          "00010370",
          ""
        ],
        "SVS": [
          "00007860",
          "3V"
        ]
      },
      "route": "00700",
      "toc": "IEC"
    }
  ],
  "R642": [
    {
      "prices": {
        "SOS": [
          "00010420",
          ""
        ],
        "SVS": [
          "00007890",
          "3V"
        ]
      },
      "route": "00700",
      "toc": "IEC"
    }
  ],
  "R652": [
    {
      "prices": {
        "SOS": [
          "00012520",
          ""
        ],
        "SVS": [
          "00009670",
          "3V"
        ]
      },
      "route": "00700",
      "toc": "IEC"
    }
  ],
  "R653": [
    {
      "prices": {
        "SOS": [
          "00012870",
          ""
        ],
        "SVS": [
          "00010000",
          "3V"
        ]
      },
      "route": "00700",
      "toc": "IEC"
    }
  ],
  "R655": [
    {
      "prices": {
        "SOS": [
          "00010190",
          ""
        ],
        "SVS": [
          "00007610",
          "3V"
        ]
      },
      "route": "00700",
      "toc": "IEC"
    }
  ],
  "R656": [
    {
      "prices": {
        "SOS": [
          "00012170",
          ""
        ],
        "SVS": [
          "00009350",
          "3V"
        ]
      },
      "route": "00700",
      "toc": "IEC"
    }
  ],
  "R657": [
    {
      "prices": {
        "SOS": [
          "00012060",
          ""
        ],
        "SVS": [
          "00009050",
          "3V"
        ]
      },
      "route": "00700",
      "toc": "IEC"
    }
  ],
  "R662": [
    {
      "prices": {
        "SOS": [
          "00010650",
          ""
        ],
        "SVS": [
          "00008010",
          "3V"
        ]
      },
      "route": "00700",
      "toc": "IEC"
    }
  ],
  "R665": [
    {
      "prices": {
        "SOS": [
          "00008860",
          ""
        ],
        "SVS": [
          "00006520",
          "3V"
        ]
      },
      "route": "00700",
      "toc": "IEC"
    }
  ],
  "R674": [
    {
      "prices": {
        "SOS": [
          "00011410",
          ""
        ],
        "SVS": [
          "00008580",
          "3V"
        ]
      },
      "route": "00700",
      "toc": "IEC"
    }
  ],
  "R680": [
    {
      "prices": {
        "SOS": [
          "00013280",
          ""
        ],
        "SVS": [
          "00010340",
          "3V"
        ]
      },
      "route": "00700",
      "toc": "IEC"
    }
  ],
  "R681": [
    {
      "prices": {
        "SOS": [
          "00013280",
          ""
        ],
        "SVS": [
          "00010340",
          "3V"
        ]
      },
      "route": "00700",
      "toc": "IEC"
    }
  ],
  "R703": [
    {
      "prices": {
        "SOS": [
          "00010190",
          ""
        ],
        "SVS": [
          "00007610",
          "3V"
        ]
      },
      "route": "00700",
      "toc": "IEC"
    }
  ],
  "R704": [
    {
      "prices": {
        "SOS": [
          "00010190",
          ""
        ],
        "SVS": [
          "00007610",
          "3V"
        ]
      },
      "route": "00700",
      "toc": "IEC"
    }
  ],
  "R901": [
    {
      "prices": {
        "SOS": [
          "00013970",
          ""
        ],
        "SVS": [
          "00011230",
          "3V"
        ]
      },
      "route": "00700",
      "toc": "IEC"
    }
  ],
  "R902": [
    {
      "prices": {
        "SOS": [
          "00014440",
          ""
        ],
        "SVS": [
          "00011390",
          "3V"
        ]
      },
      "route": "00700",
      "toc": "IEC"
    }
  ],
  "R903": [
    {
      "prices": {
        "SOS": [
          "00015240",
          ""
        ],
        "SVS": [
          "00012110",
          "3V"
        ]
      },
      "route": "00700",
      "toc": "IEC"
    }
  ],
  "R905": [
    {
      "prices": {
        "SOS": [
          "00013970",
          ""
        ],
        "SVS": [
          "00011060",
          "3V"
        ]
      },
      "route": "00700",
      "toc": "IEC"
    }
  ],
  "R907": [
    {
      "prices": {
        "SOS": [
          "00013860",
          ""
        ],
        "SVS": [
          "00010890",
          "3V"
        ]
      },
      "route": "00700",
      "toc": "IEC"
    }
  ],
  "R908": [
    {
      "prices": {
        "SOS": [
          "00013450",
          ""
        ],
        "SVS": [
          "00010550",
          "3V"
        ]
      },
      "route": "00700",
      "toc": "IEC"
    }
  ],
  "R909": [
    {
      "prices": {
        "SOS": [
          "00012870",
          ""
        ],
        "SVS": [
          "00010200",
          "3V"
        ]
      },
      "route": "00700",
      "toc": "IEC"
    }
  ],
  "R910": [
    {
      "prices": {
        "SOS": [
          "00015140",
          ""
        ],
        "SVS": [
          "00012280",
          "3V"
        ]
      },
      "route": "00700",
      "toc": "IEC"
    }
  ],
  "R911": [
    {
      "prices": {
        "SOS": [
          "00014730",
          ""
        ],
        "SVS": [
          "00011780",
          "3V"
        ]
      },
      "route": "00700",
      "toc": "IEC"
    }
  ],
  "R912": [
    {
      "prices": {
        "SOS": [
          "00014540",
          ""
        ],
        "SVS": [
          "00011570",
          "3V"
        ]
      },
      "route": "00700",
      "toc": "IEC"
    }
  ],
  "R913": [
    {
      "prices": {
        "SOS": [
          "00013630",
          ""
        ],
        "SVS": [
          "00011160",
          "3V"
        ]
      },
      "route": "00700",
      "toc": "IEC"
    }
  ],
  "R914": [
    {
      "prices": {
        "SOS": [
          "00013790",
          ""
        ],
        "SVS": [
          "00011120",
          "3V"
        ]
      },
      "route": "00700",
      "toc": "IEC"
    }
  ],
  "R920": [
    {
      "prices": {
        "SOS": [
          "00012920",
          ""
        ],
        "SVS": [
          "00010170",
          "3V"
        ]
      },
      "route": "00700",
      "toc": "IEC"
    }
  ],
  "R921": [
    {
      "prices": {
        "SOS": [
          "00012920",
          ""
        ],
        "SVS": [
          "00010170",
          "3V"
        ]
      },
      "route": "00700",
      "toc": "IEC"
    }
  ],
  "R925": [
    {
      "prices": {
        "SOS": [
          "00012920",
          ""
        ],
        "SVS": [
          "00010170",
          "3V"
        ]
      },
      "route": "00700",
      "toc": "IEC"
    }
  ],
  "R928": [
    {
      "prices": {
        "SOS": [
          "00013680",
          ""
        ],
        "SVS": [
          "00010940",
          "3V"
        ]
      },
      "route": "00700",
      "toc": "IEC"
    }
  ],
  "S039": [
    {
      "prices": {
        "SOS": [
          "00011410",
          ""
        ],
        "SVS": [
          "00008580",
          "3V"
        ]
      },
      "route": "00700",
      "toc": "IEC"
    }
  ]
}