{
  "Q108": [
    {
      "prices": {
        "CDR": [
          "00004090",
          "C4"
        ],
        "CDS": [
          "00004080",
          "C4"
        ],
        "SOR": [
          "00007320",
          ""
        ],
        "SOS": [
          "00004150",
          ""
        ],
        "SVR": [
          "00005030",
          "7B"
        ]
      },
      "route": "00000",
      "toc": "LER"
    }
  ],
  "Q368": [
    {
      "prices": {
        "SOR": [
          "00014800",
          ""
        ],
        "SOS": [
          "00009570",
          ""
        ],
        "SVR": [
          "00006710",
          "1A"
        ],
        "SVS": [
          "00006610",
          "1A"
        ]
      },
      "route": "00135",
      "toc": "LER"
    }
  ],
  "T5B1": [
    {
      "prices": {
        "CDR": [
          "00003080",
          "C4"
        ],
        "SDR": [
          "00004680",
          ""
        ],
        "SDS": [
          "00002650",
          ""
        ],
        "SVR": [
          "00004080",
          "7B"
        ]
      },
      "route": "00000",
      "toc": "LER"
    }
  ],
  "T5C1": [
    {
      "prices": {
        "CDR": [
          "00003640",
          "C4"
        ],
        "SDR": [
          "00005430",
          ""
        ],
        "SDS": [
          "00003410",
          ""
        ],
        "SVR": [
          "00004660",
          "7B"
        ]
      },
      "route": "00000",
      "toc": "LER"
    }
  ],
  "T5D1": [
    {
      "prices": {
        "CDR": [
          "00004560",
          "C4"
        ],
        "SDR": [
          "00006650",
          ""
        ],
        "SDS": [
          "00004380",
          ""
        ],
        "SOR": [
          "00008470",
          ""
        ],
        "SVR": [
          "00005210",
          "7B"
        ]
      },
      "route": "00000",
      "toc": "LER"
    }
  ],
  "T5E1": [
    {
      "prices": {
        "SOR": [
          "00011930",
          ""
        ],
        "SOS": [
          "00007690",
          ""
        ],
        "SVR": [
          "00005490",
          "9A"
        ],
        "SVS": [
          "00005390",
          "9A"
        ]
      },
      "route": "00000",
      "toc": "LER"
    }
  ],
  "T5EG": [
    {
      "prices": {
        "SOR": [
          "00012130",
          ""
        ],
        "SOS": [
          "00007570",
          ""
        ],
        "SVR": [
          "00006250",
          "9A"
        ],
        "SVS": [
          "00006150",
          "9A"
        ]
      },
      "route": "00000",
      "toc": "LER"
    }
  ],
  "T5G1": [
    {
      "prices": {
        "SOR": [
          "00013180",
          ""
        ],
        "SOS": [
          "00008350",
          ""
        ],
        "SVR": [
          "00006710",
          "9A"
        ],
        "SVS": [
          "00006610",
          "9A"
        ]
      },
      "route": "00000",
      "toc": "LER"
    }
  ]
}